LICENSE
MANIFEST.in
README.rst
setup.cfg
setup.py
test-requirements.txt
raven/__init__.py
raven/base.py
raven/context.py
raven/events.py
raven/exceptions.py
raven/middleware.py
raven/processors.py
raven/conf/__init__.py
raven/conf/defaults.py
raven/contrib/__init__.py
raven/contrib/async.py
raven/contrib/flask.py
raven/contrib/paste.py
raven/contrib/bottle/__init__.py
raven/contrib/bottle/utils.py
raven/contrib/celery/__init__.py
raven/contrib/django/__init__.py
raven/contrib/django/client.py
raven/contrib/django/handlers.py
raven/contrib/django/logging.py
raven/contrib/django/models.py
raven/contrib/django/serializers.py
raven/contrib/django/urls.py
raven/contrib/django/utils.py
raven/contrib/django/views.py
raven/contrib/django/celery/__init__.py
raven/contrib/django/celery/models.py
raven/contrib/django/celery/tasks.py
raven/contrib/django/management/__init__.py
raven/contrib/django/management/commands/__init__.py
raven/contrib/django/management/commands/raven.py
raven/contrib/django/middleware/__init__.py
raven/contrib/django/middleware/wsgi.py
raven/contrib/django/raven_compat/__init__.py
raven/contrib/django/raven_compat/handlers.py
raven/contrib/django/raven_compat/models.py
raven/contrib/django/raven_compat/management/__init__.py
raven/contrib/django/raven_compat/management/commands/__init__.py
raven/contrib/django/raven_compat/management/commands/raven.py
raven/contrib/django/raven_compat/middleware/__init__.py
raven/contrib/django/raven_compat/middleware/wsgi.py
raven/contrib/django/raven_compat/templatetags/__init__.py
raven/contrib/django/raven_compat/templatetags/raven.py
raven/contrib/django/templatetags/__init__.py
raven/contrib/django/templatetags/raven.py
raven/contrib/pylons/__init__.py
raven/contrib/tornado/__init__.py
raven/contrib/webpy/__init__.py
raven/contrib/webpy/utils.py
raven/contrib/zerorpc/__init__.py
raven/contrib/zope/__init__.py
raven/contrib/zope/component.xml
raven/data/cacert.pem
raven/handlers/__init__.py
raven_pozytywnie.egg-info/PKG-INFO
raven_pozytywnie.egg-info/SOURCES.txt
raven_pozytywnie.egg-info/dependency_links.txt
raven_pozytywnie.egg-info/entry_points.txt
raven_pozytywnie.egg-info/not-zip-safe
raven_pozytywnie.egg-info/requires.txt
raven_pozytywnie.egg-info/top_level.txt