Metadata-Version: 1.1
Name: raven-pozytywnie
Version: 5.0.0-pozytywnie0
Summary: Raven is a client for Sentry (https://www.getsentry.com)
Home-page: http://github.com/getsentry/raven-python
Author: David Cramer
Author-email: dcramer@gmail.com
License: BSD
Platform: UNKNOWN
Classifier: Intended Audience :: Developers
Classifier: Intended Audience :: System Administrators
Classifier: Operating System :: OS Independent
Classifier: Topic :: Software Development
Classifier: Programming Language :: Python
Classifier: Programming Language :: Python :: 2.6
Classifier: Programming Language :: Python :: 2.7
Classifier: Programming Language :: Python :: 3.3
Classifier: Programming Language :: Python :: 3.2
